agent_framework_azure_ai/__init__.py
agent_framework_azure_ai/_chat_client.py
agent_framework_azure_ai/_client.py
agent_framework_azure_ai/_provider.py
agent_framework_azure_ai/_shared.py
agent_framework_azure_ai/py.typed
agent_framework_azure_ai-1.0.0b260114.dist-info/licenses/LICENSE
agent_framework_azure_ai-1.0.0b260114.dist-info/WHEEL
agent_framework_azure_ai-1.0.0b260114.dist-info/METADATA
agent_framework_azure_ai-1.0.0b260114.dist-info/RECORD
